MANIFEST.in
setup.py
holmes/__init__.py
holmes/alembic.ini
holmes/cache.py
holmes/cli.py
holmes/event_bus.py
holmes/material.py
holmes/reviewer.py
holmes/search.py
holmes/server.py
holmes/utils.py
holmes/worker.py
holmes/config/__init__.py
holmes/config/babel.conf
holmes/config/local.conf
holmes/docs/Makefile
holmes/docs/conf.py
holmes/docs/facts.rst
holmes/docs/getting-started.rst
holmes/docs/index.rst
holmes/docs/violations.rst
holmes/error_handlers/__init__.py
holmes/error_handlers/sentry.py
holmes/facters/__init__.py
holmes/facters/body.py
holmes/facters/css.py
holmes/facters/google_analytics.py
holmes/facters/head.py
holmes/facters/heading_hierarchy.py
holmes/facters/images.py
holmes/facters/js.py
holmes/facters/last_modified.py
holmes/facters/links.py
holmes/facters/meta_tags.py
holmes/facters/robots.py
holmes/facters/sitemap.py
holmes/facters/title.py
holmes/handlers/__init__.py
holmes/handlers/auth.py
holmes/handlers/bus.py
holmes/handlers/domains.py
holmes/handlers/domains_violations_prefs.py
holmes/handlers/limiter.py
holmes/handlers/page.py
holmes/handlers/request.py
holmes/handlers/review.py
holmes/handlers/search.py
holmes/handlers/users.py
holmes/handlers/users_violations_prefs.py
holmes/handlers/violation.py
holmes/i18n/locale/af_ZA/LC_MESSAGES/api.mo
holmes/i18n/locale/af_ZA/LC_MESSAGES/api.po
holmes/i18n/locale/ar_SA/LC_MESSAGES/api.mo
holmes/i18n/locale/ar_SA/LC_MESSAGES/api.po
holmes/i18n/locale/ca_ES/LC_MESSAGES/api.mo
holmes/i18n/locale/ca_ES/LC_MESSAGES/api.po
holmes/i18n/locale/cs_CZ/LC_MESSAGES/api.mo
holmes/i18n/locale/cs_CZ/LC_MESSAGES/api.po
holmes/i18n/locale/da_DK/LC_MESSAGES/api.mo
holmes/i18n/locale/da_DK/LC_MESSAGES/api.po
holmes/i18n/locale/de_DE/LC_MESSAGES/api.mo
holmes/i18n/locale/de_DE/LC_MESSAGES/api.po
holmes/i18n/locale/el_GR/LC_MESSAGES/api.mo
holmes/i18n/locale/el_GR/LC_MESSAGES/api.po
holmes/i18n/locale/en_US/LC_MESSAGES/api.mo
holmes/i18n/locale/en_US/LC_MESSAGES/api.po
holmes/i18n/locale/es_ES/LC_MESSAGES/api.mo
