Metadata-Version: 1.1
Name: holmes
Version: 0.15.10
Summary: Holmes is a service to investigate your website health.
Home-page: UNKNOWN
Author: Globo.com
Author-email: appdev@corp.globo.com
License: MIT
Keywords: seo health web
Platform: UNKNOWN
Classifier: Development Status :: 4 - Beta
Classifier: Intended Audience :: Developers
Classifier: License :: OSI Approved :: MIT License
Classifier: Natural Language :: English
Classifier: Operating System :: MacOS
Classifier: Operating System :: POSIX
Classifier: Operating System :: Unix
Classifier: Operating System :: OS Independent
Classifier: Programming Language :: Python :: 2.7
